MANIFEST.in
README.md
setup.py
torille/__init__.py
torille/constants.py
torille/manual_torille.py
torille/torille.py
torille/utils.py
torille.egg-info/PKG-INFO
torille.egg-info/SOURCES.txt
torille.egg-info/dependency_links.txt
torille.egg-info/requires.txt
torille.egg-info/top_level.txt
torille/envs/__init__.py
torille/envs/duo_envs.py
torille/envs/gym_env.py
torille/envs/solo_envs.py
torille/envs/uke_envs.py
torille/toribash/.launchlock
torille/toribash/SDL2.dll
torille/toribash/SDL2_mixer.dll
torille/toribash/SDL2_ttf.dll
torille/toribash/custom.cfg
torille/toribash/default.cfg
torille/toribash/discord-rpc.dll
torille/toribash/history.log
torille/toribash/ignorelist.txt
torille/toribash/libcharset1.dll
torille/toribash/libcurl.dll
torille/toribash/libfreetype-6.dll
torille/toribash/libiconv2.dll
torille/toribash/libintl3.dll
torille/toribash/libogg-0.dll
torille/toribash/libvorbis-0.dll
torille/toribash/libvorbisfile-3.dll
torille/toribash/lua5.1.dll
torille/toribash/msvcp110.dll
torille/toribash/msvcr110.dll
torille/toribash/profile.tbs
torille/toribash/socket.lua
torille/toribash/stderr.txt
torille/toribash/temp.cfg
torille/toribash/toribash.exe
torille/toribash/zlib1.dll
torille/toribash/autosave/autosave.txt
torille/toribash/data/stats.dat
torille/toribash/data/atmospheres/Bubbles.atmo
torille/toribash/data/atmospheres/Default.atmo
torille/toribash/data/atmospheres/Garden.atmo
torille/toribash/data/atmospheres/atmo.cfg
torille/toribash/data/fonts/ascii.ttf
torille/toribash/data/fonts/chinese.ttf
torille/toribash/data/fonts/kanji.ttf
torille/toribash/data/fonts/locale.ttf
torille/toribash/data/fonts/misc.ttf
torille/toribash/data/fonts/toribash.ttf
torille/toribash/data/language/deutsch.txt
torille/toribash/data/language/english.txt
torille/toribash/data/language/french.txt
torille/toribash/data/language/portuguese.txt
torille/toribash/data/language/russian.txt
torille/toribash/data/language/spanish.txt
torille/toribash/data/language/turkish.txt
torille/toribash/data/mod/aikido.tbm
torille/toribash/data/mod/aikido3.tbm
torille/toribash/data/mod/aikido7.tbm
torille/toribash/data/mod/aikidobigdojo.tbm
