Metadata-Version: 2.1
Name: torille
Version: 1.0.2
Summary: Toribash as an agent learning environment
Home-page: https://github.com/Miffyli/ToriLLE
Author: Anssi 'Miffyli' Kanervisto
Author-email: anssk@cs.uef.fi
License: UNKNOWN
Platform: UNKNOWN
Classifier: Programming Language :: Python :: 3
Classifier: Development Status :: 5 - Production/Stable
Classifier: Operating System :: Unix
Classifier: Operating System :: Microsoft :: Windows
Classifier: Topic :: Scientific/Engineering :: Artificial Intelligence
Classifier: Intended Audience :: Science/Research
Classifier: License :: OSI Approved :: GNU General Public License v3 (GPLv3)
